bbtext.py
bbtext-0.1.0.dist-info/entry_points.txt
bbtext-0.1.0.dist-info/WHEEL
bbtext-0.1.0.dist-info/METADATA
bbtext-0.1.0.dist-info/RECORD
